{
  "configurations": [
    {
      "name": "x64-static-release",
      "generator": "Ninja",
      "configurationType": "Release",
      "inheritEnvironments": [ "msvc_x64_x64" ],
      "buildRoot": "${projectDir}\\out\\build\\${name}",
      "installRoot": "${projectDir}\\..\\..\\prebuilt\\curl-7_83_1",
      "cmakeCommandArgs": "",
      "buildCommandArgs": "",
      "ctestCommandArgs": "",
      "variables": [
        {
          "name": "CMAKE_BUILD_TYPE",
          "value": "Release",
          "type": "STRING"
        },
        {
          "name": "CURL_CA_FALLBACK",
          "value": "True",
          "type": "BOOL"
        },
        {
          "name": "BUILD_SHARED_LIBS",
          "value": "true",
          "type": "BOOL"
        },
        {
          "name": "USE_WIN32_LDAP",
          "value": "False",
          "type": "BOOL"
        },
        {
          "name": "BUILD_CURL_EXE",
          "value": "False",
          "type": "BOOL"
        },
        {
          "name": "CURL_ENABLE_SSL",
          "value": "True",
          "type": "BOOL"
        },
        {
          "name": "CURL_LTO",
          "value": "True",
          "type": "BOOL"
        },
        {
          "name": "CURL_USE_SCHANNEL",
          "value": "True",
          "type": "BOOL"
        },
        {
          "name": "ENABLE_UNIX_SOCKETS",
          "value": "False",
          "type": "BOOL"
        },
        {
          "name": "USE_LIBIDN2",
          "value": "False",
          "type": "BOOL"
        },
        {
          "name": "CURL_DISABLE_TFTP",
          "value": "True",
          "type": "BOOL"
        },
        {
          "name": "CURL_DISABLE_SMB",
          "value": "True",
          "type": "BOOL"
        },
        {
          "name": "CURL_DISABLE_FTP",
          "value": "True",
          "type": "BOOL"
        },
        {
          "name": "CURL_DISABLE_FILE",
          "value": "True",
          "type": "BOOL"
        },
        {
          "name": "CURL_DISABLE_DICT",
          "value": "True",
          "type": "BOOL"
        },
        {
          "name": "CURL_DISABLE_IMAP",
          "value": "True",
          "type": "BOOL"
        },
        {
          "name": "CURL_DISABLE_GOPHER",
          "value": "True",
          "type": "BOOL"
        },
        {
          "name": "CURL_DISABLE_MQTT",
          "value": "True",
          "type": "BOOL"
        },
        {
          "name": "CURL_DISABLE_TELNET",
          "value": "True",
          "type": "BOOL"
        },
        {
          "name": "CURL_DISABLE_SMTP",
          "value": "True",
          "type": "BOOL"
        },
        {
          "name": "CURL_DISABLE_RTSP",
          "value": "True",
          "type": "BOOL"
        },
        {
          "name": "CURL_DISABLE_POP3",
          "value": "True",
          "type": "BOOL"
        },
        {
          "name": "CURL_USE_LIBSSH2",
          "value": "False",
          "type": "BOOL"
        },
        {
          "name": "LIBCURL_OUTPUT_NAME",
          "value": "pimax-openxr-curl",
          "type": "STRING"
        }
      ]
    }
  ]
}